atspm_report/__init__.py
atspm_report/data_processing.py
atspm_report/generator.py
atspm_report/jokes.csv
atspm_report/phase_skip_processing.py
atspm_report/report_generation.py
atspm_report/statistical_analysis.py
atspm_report/table_generation.py
atspm_report/utils.py
atspm_report/visualization.py
atspm_report/images/logo.png
atspm_report/images/signal_head.png
atspm_report-0.2.0.dist-info/licenses/LICENSE
atspm_report-0.2.0.dist-info/METADATA
atspm_report-0.2.0.dist-info/WHEEL
atspm_report-0.2.0.dist-info/top_level.txt
atspm_report-0.2.0.dist-info/RECORD
