Metadata-Version: 2.4
Name: atspm-report
Version: 0.2.0
Summary: Generate ATSPM anomaly detection reports with CUSUM analysis and PDF output.
Author-email: Shawn Strasser <shawn.strasser@odot.oregon.gov>
License: MIT
Classifier: Programming Language :: Python :: 3
Classifier: License :: OSI Approved :: MIT License
Classifier: Operating System :: OS Independent
Requires-Python: >=3.9
License-File: LICENSE
Requires-Dist: pandas>=1.5.0
Requires-Dist: ibis-framework[duckdb]<12.0.0,>=11.0.0
Requires-Dist: reportlab>=4.0.0
Requires-Dist: matplotlib>=3.5.0
Provides-Extra: dev
Requires-Dist: pytest>=7.0.0; extra == "dev"
Requires-Dist: tomli; extra == "dev"
Dynamic: license-file
